CONTRIBUTING.rst
HISTORY.rst
LICENSE
MANIFEST.in
README.rst
setup.cfg
setup.py
docs/Makefile
docs/conf.py
docs/contributing.rst
docs/history.rst
docs/index.rst
docs/installation.rst
docs/make.bat
docs/readme.rst
docs/usage.rst
sample_qrzt6y2s/__init__.py
sample_qrzt6y2s/sample_qrzt6y2s.py
sample_qrzt6y2s.egg-info/PKG-INFO
sample_qrzt6y2s.egg-info/SOURCES.txt
sample_qrzt6y2s.egg-info/dependency_links.txt
sample_qrzt6y2s.egg-info/not-zip-safe
sample_qrzt6y2s.egg-info/top_level.txt
tests/__init__.py
tests/test_sample_qrzt6y2s.py