Metadata-Version: 1.1
Name: sample-qrzt6y2s
Version: 0.1.0
Summary: sample_qrzt6y2s_short_description
Home-page: https://github.com/qrZt6y2S/sample_qrzt6y2s
Author: qrZt6y2S
Author-email: qrZt6y2S@inbox.lv
License: BSD license
Keywords: sample_qrzt6y2s
Platform: UNKNOWN
Classifier: Development Status :: 2 - Pre-Alpha
Classifier: Intended Audience :: Developers
Classifier: License :: OSI Approved :: BSD License
Classifier: Natural Language :: English
Classifier: Programming Language :: Python :: 2
Classifier: Programming Language :: Python :: 2.6
Classifier: Programming Language :: Python :: 2.7
Classifier: Programming Language :: Python :: 3
Classifier: Programming Language :: Python :: 3.3
Classifier: Programming Language :: Python :: 3.4
Classifier: Programming Language :: Python :: 3.5
